pymasterstorage/DataTypes.py
pymasterstorage/__init__.py
pymasterstorage/main.py
pymasterstorage/storage.py
pymasterstorage-2.2.dist-info/LICENSE
pymasterstorage-2.2.dist-info/METADATA
pymasterstorage-2.2.dist-info/WHEEL
pymasterstorage-2.2.dist-info/top_level.txt
pymasterstorage-2.2.dist-info/RECORD
